{
  "kind": "coverage_report",
  "version": "1.0",
  "generatedAt": "2026-02-18T01:53:54.172Z",
  "sources": {
    "buildRequest": true,
    "implementationPlan": true
  },
  "requirements": {
    "total": 4,
    "implemented": 3,
    "items": [
      {
        "id": "REQ-70",
        "summary": "Stop mutating or reading the browser URL for caffeineAdminToken during initial actor creation so the app cannot hang on the startup \"Loading...\" screen.",
        "status": "missing",
        "plannedFiles": [
          "frontend/src/hooks/useActor.ts"
        ],
        "matchedFiles": []
      },
      {
        "id": "REQ-71",
        "summary": "Update actor initialization to read caffeineAdminToken only from sessionStorage and call `_initializeAccessControlWithSecret` only when a non-empty token exists.",
        "status": "implemented",
        "plannedFiles": [
          "frontend/src/hooks/useActor.ts",
          "frontend/src/utils/urlParams.ts"
        ],
        "matchedFiles": [
          "frontend/src/utils/urlParams.ts"
        ]
      },
      {
        "id": "REQ-72",
        "summary": "Make `readSecretFromHashNonMutating('caffeineAdminToken')` robust for both hash styles: (1) `#caffeineAdminToken=...` and (2) `#/route?caffeineAdminToken=...`, without mutating the URL.",
        "status": "implemented",
        "plannedFiles": [
          "frontend/src/utils/urlParams.ts"
        ],
        "matchedFiles": [
          "frontend/src/utils/urlParams.ts"
        ]
      },
      {
        "id": "REQ-73",
        "summary": "Ensure deferred token capture + URL cleanup (useDeferredUrlCleanup) is the only code path that reads caffeineAdminToken from the URL and that the cleanup runs only after mount.",
        "status": "implemented",
        "plannedFiles": [
          "frontend/src/hooks/useDeferredUrlCleanup.ts",
          "frontend/src/utils/urlParams.ts",
          "frontend/src/App.tsx"
        ],
        "matchedFiles": [
          "frontend/src/utils/urlParams.ts"
        ]
      }
    ]
  },
  "changedFiles": [
    "build-request.json",
    "feature_evidence.json",
    "frontend-implementation-plan.json",
    "frontend/src/utils/urlParams.ts",
    "project_state.json",
    "scratch/component-selection.json",
    "spec.md",
    "spec_vs_diff_report.json"
  ]
}